main.py
setup.py
physisyphus.egg-info/PKG-INFO
physisyphus.egg-info/SOURCES.txt
physisyphus.egg-info/dependency_links.txt
physisyphus.egg-info/requires.txt
physisyphus.egg-info/top_level.txt